alethic_ism_db-1.0.42.dist-info/licenses/LICENSE.md
ismdb/__init__.py
ismdb/base.py
ismdb/configmap_storage.py
ismdb/filter.py
ismdb/misc_utils.py
ismdb/monitor_storage.py
ismdb/postgres_storage_class.py
ismdb/processor_db.py
ismdb/processor_provider_storage.py
ismdb/processor_state_storage.py
ismdb/processor_storage.py
ismdb/redis_cache.py
ismdb/session_storage.py
ismdb/state_action_storage.py
ismdb/state_storage.py
ismdb/template_storage.py
ismdb/usage_storage.py
ismdb/user_project_storage.py
ismdb/user_storage.py
ismdb/vault_storage.py
ismdb/workflow_storage.py
alethic_ism_db-1.0.42.dist-info/METADATA
alethic_ism_db-1.0.42.dist-info/WHEEL
alethic_ism_db-1.0.42.dist-info/top_level.txt
alethic_ism_db-1.0.42.dist-info/RECORD
