Metadata-Version: 2.4
Name: alethic-ism-db
Version: 1.0.42
Summary: Alethic Instruction-Based State Machine (DB Python SDK)
Author-email: Kasra Rasaee <krasaee@quantumwake.io>
Project-URL: Homepage, https://github.com/quantumwake/alethic-ism-db
Classifier: Programming Language :: Python :: 3
Classifier: Operating System :: OS Independent
Requires-Python: >=3.10
License-File: LICENSE.md
Dynamic: license-file
